kpc_connector_utils/__init__.py
kpc_connector_utils/common/__init__.py
kpc_connector_utils/common/base64.py
kpc_connector_utils/common/base_config.py
kpc_connector_utils/common/context_wrapper.py
kpc_connector_utils/common/pusher.py
kpc_connector_utils/common/singleton.py
kpc_connector_utils/common/types.py
kpc_connector_utils/common/zip.py
kpc_connector_utils/connector_mssql/__init__.py
kpc_connector_utils/connector_mssql/config.py
kpc_connector_utils/pusher_s3/__init__.py
kpc_connector_utils/pusher_s3/base.py
kpc_connector_utils/pusher_s3/config.py
kpc_connector_utils/pusher_s3/data_type.py
kpc_connector_utils-0.1.19.dist-info/METADATA
kpc_connector_utils-0.1.19.dist-info/RECORD
kpc_connector_utils-0.1.19.dist-info/WHEEL
kpc_connector_utils-0.1.19.dist-info/top_level.txt
