Metadata-Version: 2.1
Name: kpc-connector-utils
Version: 0.1.19
Summary: Connector utils and configs
Home-page: https://github.com/praiwann/kpc-connector-utils
Author: Praiwan N.
Author-email: npraiwan@outlook.com
License: UNKNOWN
Platform: UNKNOWN
Classifier: Development Status :: 4 - Beta
Classifier: License :: OSI Approved :: Apache Software License
Classifier: Programming Language :: Python :: 3
